{
  "carte": "35102",
  "name": "Suzanne",
  "nb_estabs": 3,
  "estabs": [
    {
      "name": "Salon Privé Gare",
      "url": "https://www.bodypass.ch/etablissements/salon-prive/",
      "visits": 1,
      "last": "2026-03-24"
    },
    {
      "name": "Royal Savoy Hôtel &#038; Spa",
      "url": "https://www.bodypass.ch/etablissements/royal-savoy-hotel-spa/",
      "visits": 1,
      "last": "2026-03-06"
    },
    {
      "name": "Swiss Aesthetica",
      "url": "https://www.bodypass.ch/etablissements/swiss-aesthetica/",
      "visits": 1,
      "last": "2026-02-19"
    }
  ]
}