{
  "carte": "30384",
  "name": "Lena",
  "nb_estabs": 5,
  "estabs": [
    {
      "name": "Le Beausquet Genève",
      "visits": 1,
      "last": "2026-02-18",
      "last_pretty": "18 february 2026",
      "url": "https://www.bodypass.ch/etablissements/le-beausquet-geneve/"
    },
    {
      "name": "Studio Beauté",
      "visits": 1,
      "last": "2026-02-17",
      "last_pretty": "17 february 2026",
      "url": "https://www.bodypass.ch/etablissements/studio-beaute/"
    },
    {
      "name": "GLOW IN GENEVA",
      "visits": 1,
      "last": "2025-10-17",
      "last_pretty": "17 october 2025",
      "url": "https://www.bodypass.ch/etablissements/glow-in-geneva/"
    },
    {
      "name": "Blossom Institut",
      "visits": 1,
      "last": "2025-06-10",
      "last_pretty": "10 june 2025",
      "url": "https://www.bodypass.ch/etablissements/blossom-institut/"
    },
    {
      "name": "Le Cabinet de Beauté",
      "visits": 1,
      "last": "2025-06-10",
      "last_pretty": "10 june 2025",
      "url": "https://www.bodypass.ch/etablissements/le-cabinet-de-beaute/"
    }
  ]
}