{
  "carte": "33619",
  "name": "Barbara",
  "nb_estabs": 3,
  "estabs": [
    {
      "name": "EUPHORIA &#038; BEAUTY STUDIO",
      "visits": 1,
      "last": "2025-12-22",
      "last_pretty": "22 december 2025",
      "url": "https://www.bodypass.ch/etablissements/euphoria-beauty-studio/"
    },
    {
      "name": "Akyado Genève Centre",
      "visits": 1,
      "last": "2025-08-05",
      "last_pretty": "05 august 2025"
    },
    {
      "name": "SAKURA LAB",
      "visits": 1,
      "last": "2025-07-25",
      "last_pretty": "25 july 2025",
      "url": "https://www.bodypass.ch/etablissements/sakura-lab/"
    }
  ]
}