{
  "carte": "34715",
  "name": "Cindy",
  "nb_estabs": 9,
  "estabs": [
    {
      "name": "LES TRESOMS",
      "visits": 1,
      "last": "2026-04-22",
      "last_pretty": "22 april 2026"
    },
    {
      "name": "So Hair",
      "visits": 1,
      "last": "2026-03-31",
      "last_pretty": "31 march 2026"
    },
    {
      "name": "BLISS",
      "visits": 1,
      "last": "2026-03-24",
      "last_pretty": "24 march 2026"
    },
    {
      "name": "Sawatdee Delices",
      "visits": 1,
      "last": "2026-01-24",
      "last_pretty": "24 january 2026"
    },
    {
      "name": "Hôtel Intercontinental Spa 5 Mondes",
      "visits": 1,
      "last": "2025-11-07",
      "last_pretty": "07 november 2025"
    },
    {
      "name": "SAKURA LAB",
      "visits": 1,
      "last": "2025-10-13",
      "last_pretty": "13 october 2025"
    },
    {
      "name": "VAGHEGGI Phyto Space Crans-Montana",
      "visits": 1,
      "last": "2025-09-11",
      "last_pretty": "11 september 2025"
    },
    {
      "name": "EVERNESS <br>Hôtel &#038; Resort",
      "visits": 1,
      "last": "2025-09-03",
      "last_pretty": "03 september 2025"
    },
    {
      "name": "Guinot Art of Beauty",
      "visits": 1,
      "last": "2025-07-24",
      "last_pretty": "24 july 2025"
    }
  ]
}