{
  "carte": "35677",
  "name": "Maria",
  "nb_estabs": 3,
  "estabs": [
    {
      "name": "LE CENTRE GENÈVE BY CHARLINE",
      "url": "https://www.bodypass.ch/etablissements/le-centre-geneve-by-charline/",
      "visits": 1,
      "last": "2026-04-08"
    },
    {
      "name": "SUBLIMEYES",
      "url": "https://www.bodypass.ch/etablissements/institut-sublimeyes/",
      "visits": 1,
      "last": "2026-03-28"
    },
    {
      "name": "GLOW IN GENEVA",
      "url": "https://www.bodypass.ch/etablissements/glow-in-geneva/",
      "visits": 1,
      "last": "2026-02-16"
    }
  ]
}