{
  "carte": "27098",
  "name": "Marco",
  "nb_estabs": 3,
  "estabs": [
    {
      "name": "Namaka &#8211; Centre de Longévité et Bienêtre",
      "url": "https://www.bodypass.ch/etablissements/namaka/",
      "visits": 1,
      "last": "2026-01-02"
    },
    {
      "name": "EVERNESS <br>Hôtel &#038; Resort",
      "url": "https://www.bodypass.ch/etablissements/everness-resort/",
      "visits": 1,
      "last": "2025-12-26"
    },
    {
      "name": "Nirvana Spa",
      "url": "https://www.bodypass.ch/?s=Nirvana%20Spa",
      "visits": 1,
      "last": "2025-08-09"
    }
  ]
}