{
  "carte": "30715",
  "name": "Nancy",
  "nb_estabs": 3,
  "estabs": [
    {
      "name": "Bains d&rsquo;Ovronnaz",
      "url": "https://www.bodypass.ch/etablissements/bains-dovronnaz/",
      "visits": 1,
      "last": "2026-05-10"
    },
    {
      "name": "FLEUR D’EPIDERME",
      "url": "https://www.bodypass.ch/etablissements/fleur-depiderme/",
      "visits": 1,
      "last": "2026-03-10"
    },
    {
      "name": "GLOW IN GENEVA",
      "url": "https://www.bodypass.ch/etablissements/glow-in-geneva/",
      "visits": 1,
      "last": "2025-09-09"
    }
  ]
}