{
  "carte": "29248",
  "name": "Maissa",
  "nb_estabs": 5,
  "estabs": [
    {
      "name": "Arte Beauty EHL",
      "url": "https://www.bodypass.ch/etablissements/arte-beauty-ehl/",
      "visits": 1,
      "last": "2026-02-26"
    },
    {
      "name": "Arte Beauty Lutry",
      "url": "https://www.bodypass.ch/etablissements/arte-beauty-lutry/",
      "visits": 1,
      "last": "2025-07-21"
    },
    {
      "name": "Maison Perle",
      "url": "https://www.bodypass.ch/etablissements/maison-perle/",
      "visits": 1,
      "last": "2025-07-02"
    },
    {
      "name": "Arte Beauty EPFL",
      "url": "https://www.bodypass.ch/etablissements/arte-beauty-epfl/",
      "visits": 1,
      "last": "2025-06-25"
    },
    {
      "name": "Nail Café",
      "url": "https://www.bodypass.ch/etablissements/nail-cafe/",
      "visits": 1,
      "last": "2025-05-28"
    }
  ]
}