{
  "carte": "33186",
  "name": "pascal",
  "nb_estabs": 3,
  "estabs": [
    {
      "name": "CJ Coiffure",
      "url": "https://www.bodypass.ch/etablissements/cj-coiffure/",
      "visits": 1,
      "last": "2026-02-18"
    },
    {
      "name": "Atmosp&rsquo;hair",
      "url": "https://www.bodypass.ch/etablissements/atmosphair/",
      "visits": 1,
      "last": "2026-02-17"
    },
    {
      "name": "Salon Privé Gare",
      "url": "https://www.bodypass.ch/etablissements/salon-prive/",
      "visits": 1,
      "last": "2025-08-30"
    }
  ]
}