{
  "carte": "26398",
  "name": "David",
  "nb_estabs": 3,
  "estabs": [
    {
      "name": "Les Sources du Chéry",
      "url": "https://www.bodypass.ch/etablissements/les-sources-du-chery/",
      "visits": 1,
      "last": "2026-03-14"
    },
    {
      "name": "Chalet-Hôtel la Marmotte",
      "url": "https://www.bodypass.ch/etablissements/chalet-hotel-la-marmotte/",
      "visits": 1,
      "last": "2026-01-10"
    },
    {
      "name": "Deep Nature Les Granges d&rsquo;en Haut",
      "url": "https://www.bodypass.ch/etablissements/deep-nature-les-granges-den-haut/",
      "visits": 1,
      "last": "2025-07-12"
    }
  ]
}