{
  "carte": "33285",
  "name": "Lucy",
  "nb_estabs": 3,
  "estabs": [
    {
      "name": "Arte Beauty Lutry",
      "url": "https://www.bodypass.ch/etablissements/arte-beauty-lutry/",
      "visits": 1,
      "last": "2026-01-27"
    },
    {
      "name": "Salon Privé Gare",
      "url": "https://www.bodypass.ch/etablissements/salon-prive/",
      "visits": 1,
      "last": "2025-10-11"
    },
    {
      "name": "Arte Beauty EPFL",
      "url": "https://www.bodypass.ch/etablissements/arte-beauty-epfl/",
      "visits": 1,
      "last": "2025-06-25"
    }
  ]
}