{
  "carte": "31602",
  "name": "Mona",
  "nb_estabs": 10,
  "estabs": [
    {
      "name": "EUPHORIA &#038; BEAUTY STUDIO",
      "url": "https://www.bodypass.ch/etablissements/euphoria-beauty-studio/",
      "visits": 1,
      "last": "2025-12-29"
    },
    {
      "name": "LE CENTRE GENÈVE BY CHARLINE",
      "url": "https://www.bodypass.ch/etablissements/le-centre-geneve-by-charline/",
      "visits": 1,
      "last": "2025-12-23"
    },
    {
      "name": "LE CENTRE GENÈVE BY CHARLINE &#8211; Eva",
      "url": "https://www.bodypass.ch/?s=LE%20CENTRE%20GEN%C3%88VE%20BY%20CHARLINE%20%E2%80%93%20Eva",
      "visits": 1,
      "last": "2025-12-22"
    },
    {
      "name": "So Hair",
      "url": "https://www.bodypass.ch/etablissements/so-hair/",
      "visits": 1,
      "last": "2025-10-10"
    },
    {
      "name": "BLISS",
      "url": "https://www.bodypass.ch/etablissements/bliss/",
      "visits": 1,
      "last": "2025-10-07"
    },
    {
      "name": "Spa Baron Tavernier",
      "url": "https://www.bodypass.ch/?s=Spa%20Baron%20Tavernier",
      "visits": 1,
      "last": "2025-08-27"
    },
    {
      "name": "SAKURA LAB",
      "url": "https://www.bodypass.ch/etablissements/sakura-lab/",
      "visits": 1,
      "last": "2025-07-29"
    },
    {
      "name": "Le Beausquet Genève",
      "url": "https://www.bodypass.ch/etablissements/le-beausquet-geneve/",
      "visits": 1,
      "last": "2025-07-16"
    },
    {
      "name": "Akyado Genève Centre",
      "url": "https://www.bodypass.ch/?s=Akyado%20Gen%C3%A8ve%20Centre",
      "visits": 1,
      "last": "2025-07-14"
    },
    {
      "name": "Organik Beauty",
      "url": "https://www.bodypass.ch/etablissements/organik-beauty/",
      "visits": 1,
      "last": "2025-05-30"
    }
  ]
}