{
  "carte": "30243",
  "name": "Margot",
  "nb_estabs": 4,
  "estabs": [
    {
      "name": "FLEUR D’EPIDERME",
      "visits": 1,
      "last": "2026-03-20",
      "last_pretty": "20 march 2026",
      "url": "https://www.bodypass.ch/etablissements/fleur-depiderme/"
    },
    {
      "name": "Parallèles Coiffure",
      "visits": 1,
      "last": "2025-12-23",
      "last_pretty": "23 december 2025",
      "url": "https://www.bodypass.ch/etablissements/paralleles-coiffure/"
    },
    {
      "name": "Skin Solution",
      "visits": 1,
      "last": "2025-07-05",
      "last_pretty": "05 july 2025",
      "url": "https://www.bodypass.ch/etablissements/skin-solution/"
    },
    {
      "name": "Le Bal des Créateurs",
      "visits": 1,
      "last": "2025-06-13",
      "last_pretty": "13 june 2025",
      "url": "https://www.bodypass.ch/etablissements/le-bal-des-createurs-3/"
    }
  ]
}