{
  "carte": "35197",
  "name": "Charlie",
  "nb_estabs": 2,
  "estabs": [
    {
      "name": "Chalet Royalp Hôtel &#038; Spa",
      "visits": 1,
      "last": "2026-04-16",
      "last_pretty": "16 april 2026",
      "url": "https://www.bodypass.ch/etablissements/chalet-royalp-hotel-spa/"
    },
    {
      "name": "Arte Beauty Lutry",
      "visits": 1,
      "last": "2026-03-20",
      "last_pretty": "20 march 2026",
      "url": "https://www.bodypass.ch/etablissements/arte-beauty-lutry/"
    }
  ]
}