{
  "carte": "30524",
  "name": "Maude",
  "nb_estabs": 2,
  "estabs": [
    {
      "name": "Le Mirador Resort &#038; Spa",
      "visits": 1,
      "last": "2026-02-27",
      "last_pretty": "27 february 2026",
      "url": "https://www.bodypass.ch/etablissements/le-mirador-resort-spa/"
    },
    {
      "name": "Institut Sirène",
      "visits": 1,
      "last": "2025-07-10",
      "last_pretty": "10 july 2025",
      "url": "https://www.bodypass.ch/etablissements/institut-sirene/"
    }
  ]
}