{
  "carte": "39270",
  "name": "Isabelle",
  "nb_estabs": 4,
  "estabs": [
    {
      "name": "Salon Privé Ecublens",
      "url": "https://www.bodypass.ch/etablissements/salon-prive-ecublens/",
      "visits": 1,
      "last": "2026-05-13"
    },
    {
      "name": "NUTRITION SANTE JULIETTE",
      "url": "https://www.bodypass.ch/etablissements/nutrition-sante-juliette/",
      "visits": 1,
      "last": "2026-01-30"
    },
    {
      "name": "JOIA LAUSANNE",
      "url": "https://www.bodypass.ch/etablissements/joia-lausanne/",
      "visits": 1,
      "last": "2026-01-26"
    },
    {
      "name": "Nueva Luna Yoga",
      "url": "https://www.bodypass.ch/etablissements/nueva-luna-yoga/",
      "visits": 1,
      "last": "2026-01-22"
    }
  ]
}